Metadata-Version: 1.1
Name: Pillow3f
Version: 0.0.4
Summary: 3D graphics library using Pillow
Home-page: UNKNOWN
Author: Robert Bassett
Author-email: bassett.w.robert@gmail.com
License: UNKNOWN
Platform: UNKNOWN
Classifier: Programming Language :: Python :: 3
Classifier: Operating System :: OS Independent
